finml_utils/__init__.py
finml_utils/backtest.py
finml_utils/columns.py
finml_utils/correlation.py
finml_utils/dataclass.py
finml_utils/dataframes.py
finml_utils/dict.py
finml_utils/enums.py
finml_utils/env.py
finml_utils/factor.py
finml_utils/files.py
finml_utils/forward.py
finml_utils/introspection.py
finml_utils/jsonencodable.py
finml_utils/list.py
finml_utils/metrics.py
finml_utils/obj.py
finml_utils/p_tqdm.py
finml_utils/parallel.py
finml_utils/path.py
finml_utils/returns.py
finml_utils/s3_store.py
finml_utils/shuffle.py
finml_utils/signal.py
finml_utils/splitters.py
finml_utils/stats.py
finml_utils/transformations.py
finml_utils/window.py
finml_utils/quantstats/__init__.py
finml_utils/quantstats/logo.svg
finml_utils/quantstats/report.html
finml_utils/quantstats/reports.py
finml_utils/quantstats/stats.py
finml_utils/quantstats/utils.py
finml_utils/quantstats/plotting/__init__.py
finml_utils/quantstats/plotting/core.py
finml_utils/quantstats/plotting/wrappers.py
finml_utils-4.1.2.dist-info/METADATA
finml_utils-4.1.2.dist-info/WHEEL
finml_utils-4.1.2.dist-info/RECORD
